README.rst
setup.py
nebnr/__init__.py
nebnr/api.py
nebnr.egg-info/PKG-INFO
nebnr.egg-info/SOURCES.txt
nebnr.egg-info/dependency_links.txt
nebnr.egg-info/top_level.txt
nebnr.egg-info/zip-safe